{
  "timestamp": "2026-03-29T23:01:23.931828",
  "sensors": {
    "timestamp": "2026-03-29 23:01:23",
    "temp": 33.0,
    "hum": 35.0,
    "light": 899,
    "p1": 575,
    "p2": 125,
    "p3": 451
  },
  "moisture_analysis": {
    "p1": {
      "moisture_pct": 46.6,
      "is_dry": false
    },
    "p2": {
      "moisture_pct": 100,
      "is_dry": false
    },
    "p3": {
      "moisture_pct": 63.5,
      "is_dry": false
    }
  },
  "environment": {
    "vpd_kpa": 3.269
  },
  "intelligence": {
    "hypothesis": "Soil moisture is adequate, but atmospheric demand remains high.",
    "active_concerns": [
      "high-vpd"
    ],
    "temporal_stack": {
      "anchor": "/Users/surendran/.openclaw/workspace/gardenbot/archive/2026-03-29/garden_084645.jpg",
      "previous": "/Users/surendran/.openclaw/workspace/gardenbot/archive/2026-03-29/garden_202208.jpg",
      "current": "/Users/surendran/.openclaw/workspace/gardenbot/media/latest.jpg"
    },
    "vision_observation": {
      "timestamp": "2026-03-29T17:52:19.367064",
      "model": "gemma-3-27b-it",
      "image_availability": {
        "compare_set": [
          "/Users/surendran/.openclaw/workspace/gardenbot/archive/2026-03-25/garden_145000.jpg",
          "/Users/surendran/.openclaw/workspace/gardenbot/archive/2026-03-26/garden_135001.jpg",
          "/Users/surendran/.openclaw/workspace/gardenbot/archive/2026-03-27/garden_135000.jpg",
          "/Users/surendran/.openclaw/workspace/gardenbot/archive/2026-03-28/garden_133431.jpg",
          "/Users/surendran/.openclaw/workspace/gardenbot/archive/2026-03-29/garden_084645.jpg",
          "/Users/surendran/.openclaw/workspace/gardenbot/archive/2026-03-29/garden_125751.jpg",
          "/Users/surendran/.openclaw/workspace/gardenbot/archive/2026-03-29/garden_175153.jpg"
        ],
        "current": "/Users/surendran/.openclaw/workspace/gardenbot/archive/2026-03-29/garden_175153.jpg",
        "anchor": "/Users/surendran/.openclaw/workspace/gardenbot/archive/2026-03-25/garden_145000.jpg",
        "previous": "/Users/surendran/.openclaw/workspace/gardenbot/archive/2026-03-29/garden_125751.jpg"
      },
      "frame_sequence": [
        {
          "label": "EARLIEST",
          "path": "/Users/surendran/.openclaw/workspace/gardenbot/archive/2026-03-25/garden_145000.jpg"
        },
        {
          "label": "T-5",
          "path": "/Users/surendran/.openclaw/workspace/gardenbot/archive/2026-03-26/garden_135001.jpg"
        },
        {
          "label": "T-4",
          "path": "/Users/surendran/.openclaw/workspace/gardenbot/archive/2026-03-27/garden_135000.jpg"
        },
        {
          "label": "T-3",
          "path": "/Users/surendran/.openclaw/workspace/gardenbot/archive/2026-03-28/garden_133431.jpg"
        },
        {
          "label": "T-2",
          "path": "/Users/surendran/.openclaw/workspace/gardenbot/archive/2026-03-29/garden_084645.jpg"
        },
        {
          "label": "T-1",
          "path": "/Users/surendran/.openclaw/workspace/gardenbot/archive/2026-03-29/garden_125751.jpg"
        },
        {
          "label": "CURRENT",
          "path": "/Users/surendran/.openclaw/workspace/gardenbot/archive/2026-03-29/garden_175153.jpg"
        }
      ],
      "vision_report": {
        "timestamp": "2026-03-29T18:00:00Z",
        "model": "Garden Botanical Observer v1.0",
        "plant_audit": {
          "p1": {
            "physical_facts": "Numerous small, round leaves densely packed. Leaves are a consistent pale green color. No visible changes in leaf count or posture across the sequence. Leaves appear slightly dusty.",
            "explanatory_transformations": "No significant changes observed in p1 over the past 5 days. Leaf turgor appears stable.",
            "pixel_based_health_reasoning": "Consistent color and leaf structure suggest stable health. Dust accumulation may indicate a lack of air circulation, but is not immediately detrimental.",
            "leaf_count": "Approximately 30-40 leaves",
            "leaf_color": "Pale Green",
            "leaf_posture": "Erect, slightly cascading"
          },
          "p2": {
            "physical_facts": "Two large, broad leaves initially present. Smaller leaves emerging from the center. One of the large leaves shows a developing brown spot. The brown spot is expanding over time.",
            "explanatory_transformations": "The brown spot on the larger leaf has increased in size from T-5 to CURRENT. The smaller leaves have grown slightly, but appear pale.",
            "pixel_based_health_reasoning": "The expanding brown spot indicates a localized infection or nutrient deficiency. Pale color of new leaves suggests insufficient light or nutrient uptake. The plant is showing signs of stress.",
            "leaf_count": "2 large, 2 small",
            "leaf_color": "Dark Green (large), Pale Green (small), Brown (spot)",
            "leaf_posture": "Erect"
          },
          "p3": {
            "physical_facts": "Two leaves present. The rabbit toy is positioned near the base of the plant. Leaves are a dark green color. No significant changes in leaf size or posture.",
            "explanatory_transformations": "Minimal growth observed in p3. Leaves remain relatively stable in position and color.",
            "pixel_based_health_reasoning": "Stable leaf color and posture suggest adequate health. Slow growth may indicate limited resources or suboptimal conditions.",
            "leaf_count": "2",
            "leaf_color": "Dark Green",
            "leaf_posture": "Erect"
          },
          "p4": {
            "physical_facts": "Very small plant, almost entirely obscured by p2. Difficult to discern individual leaves. Appears to be a small sprout.",
            "explanatory_transformations": "No discernible changes in p4 due to its small size and obscured position.",
            "pixel_based_health_reasoning": "Insufficient data to assess health due to limited visibility.",
            "leaf_count": "Unknown",
            "leaf_color": "Pale Green",
            "leaf_posture": "Prostrate"
          }
        },
        "biome_observations": {
          "soil_texture": "Appears consistently dry and compacted in all pots. No visible cracking or dampness.",
          "incidental_growth": "No weeds, moss, or secondary seedlings observed in any of the pots.",
          "debris": "Some small pieces of debris (likely plant matter) scattered on the desk surface.",
          "fungal_presence": "No visible fungal growth observed."
        },
        "temporal_deltas": {
          "p2_brown_spot_growth": "Increased by approximately 2mm in diameter over 5 days.",
          "p3_growth": "Negligible growth observed.",
          "p4_visibility": "Remains consistently obscured."
        },
        "visual_health_inference": "Overall, the biome appears relatively stable, but p2 is exhibiting signs of stress due to the developing brown spot. P3 is showing very slow growth. P1 appears healthy but may benefit from improved air circulation. P4 is too small to assess.",
        "anomalies": [
          "Expanding brown spot on p2 leaf.",
          "Dry and compacted soil in all pots.",
          "Slow growth of p3."
        ],
        "narrative_description": "The garden is showing subtle changes over the past 5 days. The most significant observation is the progression of the brown spot on the Mexican Mint (p2), indicating a potential health issue. The String of Nickels (p1) remains stable, while the Pothos (p3) exhibits minimal growth. The Silver Guest (p4) is difficult to assess due to its size and position. The soil appears dry, suggesting a need for increased watering.",
        "confidence": 0.85
      }
    },
    "recent_visual_ledger": [
      "\ud83e\udeb4 Individual Plant Status\n* **p1 (String of Nickels):** Healthy - Alignment (sensor shows 51.8% moisture adequate and visuals show healthy, stable growth) \u2794 **Advice:** Continue foliar misting to mitigate VPD stress; monitor for any changes\n* **p2 (Mexican Mint):** Stress - Divergence (sensor shows 100% moisture ample but visuals reveal expanding brown spot and pale new leaves indicating stress) \u2794 **Advice:** Check for overwatering; allow topsoil to dry slightly; inspect for pests/nutrient deficiency; consider foliar feeding\n* **p3 (Pothos):** Healthy - Alignment (sensor shows 62.7% moisture adequate and visuals show stable, healthy growth) \u2794 **Advice:** Continue foliar misting for VPD stress; maintain current care\n* **p4 (Silver Guest):** Stress - Divergence (sensor shows 100% moisture ample (shared with p2) but visuals show pale color and obscured growth suggesting insufficient light or nutrient deficiency) \u2794 **Advice:** Consider increasing light exposure (move closer to window or add grow light); inspect for nutrient deficiency",
      "\ud83c\udf21\ufe0f Biome Dynamics\n* **VPD Context:** EXTREME at 3.269 kPa, indicating high atmospheric demand causing transpiration stress despite adequate soil moisture.\n* **The Warden's Verdict:** Soil moisture remains ample across all plants, but extreme VPD (3.269 kPa) drives transpiration stress; visual stress on p2 and p4 diverges from sensor readings, suggesting issues beyond hydration (overwatering/biological issue for p2, light deficiency for p4). p1 and p3 show alignment and remain healthy.",
      "\ud83d\udcbe STATE UPDATE (INTERNAL)\n- **NEW_HYPOTHESIS**: Addressing the brown spot on p2 through inspection and possible treatment, and increasing light for p4, will mitigate the observed visual stresses.\n- **LAST_HUMAN_ACTION**: queried p2\n- **ACTIVE CONCERNS**: high-vpd, p2-brown-spot, p4-insufficient-light"
    ]
  }
}