{
  "timestamp": "2026-03-27T06:56:02.952284",
  "sensors": {
    "timestamp": "2026-03-27 06:56:02",
    "temp": 32.0,
    "hum": 36.0,
    "light": 782,
    "p1": 507,
    "p2": 207,
    "p3": 352
  },
  "moisture_analysis": {
    "p1": {
      "moisture_pct": 67.5,
      "is_dry": false
    },
    "p2": {
      "moisture_pct": 99.1,
      "is_dry": false
    },
    "p3": {
      "moisture_pct": 91.7,
      "is_dry": false
    }
  },
  "environment": {
    "vpd_kpa": 3.043
  },
  "intelligence": {
    "recent_visual_ledger": [
      "WARDEN REPORT - 2026-03-27 06:03\n\n**Vitality Pulse**: p1-p4 Status: All plants exhibit turgid foliage with no signs of wilting or discoloration. p4 retains a stable, localized wilting on one lower leaf unchanged from prior observations.\n\n**The Biome Discovery**: Non-plant observation: Soil surface appears uniformly moist with no exposed wiring or artificial structures visible; shadow angles indicate early morning light consistent with timestamp.\n\n**Growth Momentum**: Pothos (p3) shows approximately 2-3 mm apical growth since yesterday's baseline. Mexican Mint (p2) exhibits minimal growth, approximately 1 mm. No new leaves observed on either plant.\n\n**Weather Alignment**: Forecast indicates mist with temperatures 26-27\u00b0C and humidity 75-84"
    ]
  }
}